Metadata-Version: 1.1
Name: rilly
Version: 0.1.1
Summary: Change Data Capture Python library for BigQuery
Home-page: https://github.com/manesioz/rilly
Author: Zachary Manesiotis
Author-email: zack.manesiotis@gmail.com
License: MIT
Download-URL: https://github.com/manesioz/rilly/archive/v0.1.1.tar.gz
Keywords: chn=ange-data-capture,python,bigquery,kafka,pubsub,distributed-system
Platform: UNKNOWN
Classifier: Development Status :: 3 - Alpha
Classifier: Intended Audience :: Developers
Classifier: Topic :: Software Development :: Build Tools
Classifier: License :: OSI Approved :: MIT License
Classifier: Programming Language :: Python :: 3
Classifier: Programming Language :: Python :: 3.4
Classifier: Programming Language :: Python :: 3.5
Classifier: Programming Language :: Python :: 3.6
